journal_brief/__init__.py
journal_brief/config.py
journal_brief/constants.py
journal_brief/filter.py
journal_brief/journal_brief.py
journal_brief/cli/__init__.py
journal_brief/cli/constants.py
journal_brief/cli/main.py
journal_brief/format/__init__.py
journal_brief/format/config.py
journal_brief/format/json.py
journal_brief/format/login.py
journal_brief/format/reboot.py
journal_brief/format/short.py
journal_brief/format/systemd.py
journal_brief-1.1.8.dist-info/LICENSE
journal_brief-1.1.8.dist-info/METADATA
journal_brief-1.1.8.dist-info/WHEEL
journal_brief-1.1.8.dist-info/entry_points.txt
journal_brief-1.1.8.dist-info/top_level.txt
journal_brief-1.1.8.dist-info/RECORD
