Metadata-Version: 2.1
Name: journal-brief
Version: 1.1.8
Summary: Show interesting new systemd journal entries since last run
Home-page: https://github.com/twaugh/journal-brief
Author: Tim Waugh
Author-email: tim@cyberelk.net
License: GPLv2+
Keywords: systemd journal journalctl log monitor watch
Platform: UNKNOWN
Classifier: Development Status :: 5 - Production/Stable
Classifier: Environment :: Console
Classifier: Intended Audience :: System Administrators
Classifier: License :: OSI Approved :: GNU General Public License v2 or later (GPLv2+)
Classifier: Operating System :: POSIX :: Linux
Classifier: Programming Language :: Python :: 3 :: Only
Classifier: Topic :: System :: Logging
Classifier: Topic :: System :: Monitoring
License-File: LICENSE
Requires-Dist: PyYAML
Requires-Dist: systemd-python
